decision_segment/__init__.py
decision_segment/__main__.py
decision_segment/popover.py
decision_segment-0.0.3.dist-info/WHEEL
decision_segment-0.0.3.dist-info/METADATA
decision_segment-0.0.3.dist-info/RECORD
